{
  "nameShort": "PocketShell",
  "nameLong": "PocketShell",
  "applicationName": "pocketshell",
  "dataFolderName": ".pocketshell",
  "sharedDataFolderName": ".pocketshell-shared",
  "win32MutexName": "pocketshell",
  "licenseName": "MIT",
  "licenseUrl": "https://github.com/alexeygrigorev/pocketshell-desktop/blob/main/LICENSE",
  "serverLicenseUrl": "https://github.com/alexeygrigorev/pocketshell-desktop/blob/main/LICENSE",
  "serverGreeting": [],
  "serverLicense": [],
  "serverLicensePrompt": "",
  "serverApplicationName": "pocketshell-server",
  "serverDataFolderName": ".pocketshell-server",
  "tunnelApplicationName": "pocketshell-tunnel",
  "win32DirName": "PocketShell",
  "win32NameVersion": "PocketShell",
  "win32RegValueName": "PocketShell",
  "win32x64AppId": "{{D77B7E06-80BA-4137-BCF4-654B95CCEBC5}",
  "win32arm64AppId": "{{D1ACE434-89C5-48D1-88D3-E2991DF85475}",
  "win32x64UserAppId": "{{CC6B787D-37A0-49E8-AE24-8559A032BE0C}",
  "win32arm64UserAppId": "{{3AEBF0C8-F733-4AD4-BADE-FDB816D53D7B}",
  "win32AppUserModelId": "PocketShell.App",
  "win32ShellNameShort": "&PocketShell",
  "win32TunnelServiceMutex": "pocketshell-tunnelservice",
  "win32TunnelMutex": "pocketshell-tunnel",
  "darwinBundleIdentifier": "com.pocketshell.app",
  "darwinProfileUUID": "47827DD9-4734-49A0-AF80-7E19B11495CC",
  "darwinProfilePayloadUUID": "CF808BE7-53F3-46C6-A7E2-7EDB98A5E959",
  "linuxIconName": "pocketshell",
  "licenseFileName": "LICENSE.txt",
  "reportIssueUrl": "https://github.com/alexeygrigorev/pocketshell-desktop/issues/new",
  "nodejsRepository": "https://nodejs.org",
  "urlProtocol": "pocketshell",
  "enableTelemetry": false,
  "extensionsGallery": {
    "serviceUrl": "https://open-vsx.org/vscode/gallery",
    "itemUrl": "https://open-vsx.org/vscode/item",
    "resourceUrlTemplate": "https://open-vsx.org/vscode/unpkg/{publisher}/{name}/{version}/{path}",
    "controlUrl": "",
    "recommendationsUrl": ""
  },
  "extensionEnabledApiProposals": {},
  "builtInExtensions": [],
  "defaultChatAgent": {
    "extensionId": "GitHub.copilot",
    "chatExtensionId": "GitHub.copilot-chat",
    "provider": {
      "default": { "id": "github", "name": "GitHub" },
      "enterprise": { "id": "github-enterprise", "name": "GitHub Enterprise" }
    },
    "providerScopes": []
  },
  "trustedExtensionAuthAccess": {},
  "builtInExtensionsEnabledWithAutoUpdates": [],
  "sessionsWindowAllowedExtensions": [],
  "quality": "stable",
  "documentationUrl": "https://github.com/alexeygrigorev/pocketshell-desktop#readme",
  "removeTelemetry": true
}
